PythonCrypto.py
PythonCrypto-1.1.dist-info/LICENSE.txt
PythonCrypto-1.1.dist-info/METADATA
PythonCrypto-1.1.dist-info/WHEEL
PythonCrypto-1.1.dist-info/top_level.txt
PythonCrypto-1.1.dist-info/RECORD
