Metadata-Version: 2.1
Name: PythonCrypto
Version: 1.1
Summary: NORMAL TEXT TO CIPHER TEXT
Home-page: https://github.com/WIZARD00007/PyCrypto.git
Author: Akshay
Author-email: akshaysavanoor@gmail.com
License: UNKNOWN
Platform: UNKNOWN
Classifier: Programming Language :: Python :: 3
Classifier: Programming Language :: Python :: 3.7
Classifier: Programming Language :: Python :: 3.10
Classifier: License :: OSI Approved :: GNU General Public License v2 or later (GPLv2+)
Classifier: Operating System :: OS Independent
License-File: LICENSE.txt
Requires-Dist: blessings (~=1.7)
